{
  "id": 8171,
  "title": "New: The Horrors – Still Life",
  "date": "2011-05-24T23:13:12",
  "body": "[![](http://admin.crackintheroad.com/wp-content/uploads/2011/05/thehorrorsstillife.jpg \"thehorrorsstillife\")](http://admin.crackintheroad.com/music/8171-new-the-horrors-still-life/attachment/thehorrorsstillife)  \nOn July 26 all our questions will be answered in the form of a brand new LP. But for now we have this synth/string-laden delight. At times it’s painfully obvious, at others it’s flourishingly creepy and perverse. Check it out bellow.",
  "image": {
    "url": null,
    "srcset": false
  },
  "excerpt": {
    "full": "On July 26 all our questions will be answered in the form of a brand new LP. But for now we have this synth/string-laden delight. At times it’s painfully obvious, at others it’s flourishingly creepy and perverse. Check it out bellow.",
    "short": "\r\nOn July 26 all our questions will be answered in the form of a brand new LP."
  },
  "author": 3,
  "categories": [
    301
  ],
  "tags": [
    1926,
    362
  ],
  "featured": false
}