{
  "id": 9118,
  "title": "New: Freddie Joachim – Waves",
  "date": "2011-07-09T17:52:30",
  "body": "Photo By [Shelbie Dimond](http://www.flickr.com/photos/theciscokid/)  \n**Freddie Joachim’s** work often comes across as a musical stream of consciousness; it floats blissfully through time, appearing heavily improvised while delicately constructed. His new piece, _Waves_, does exactly what it says on the tin; it’s a glamorous jazz number that’s perfect for a summer’s day.\n\nStream it below.\n\n [Freddie Joachim – Waves](http://soundcloud.com/freddiejoachim/freddie-joachim-waves) by [freddiejoachim](http://soundcloud.com/freddiejoachim)",
  "image": {
    "url": null,
    "srcset": false
  },
  "excerpt": {
    "full": "Photo By Shelbie Dimond Freddie Joachim’s work often comes across as a musical stream of consciousness; it floats blissfully through time, appearing heavily improvised while delicately constructed. His new piece, Waves, does exactly what it says on the tin; it’s a glamorous jazz number that’s perfect for a summer’s day. Stream it below. Freddie Joachim \\[…\\]",
    "short": "Photo By Shelbie Dimond\r\nFreddie Joachim’s work often comes across as a musical stream o..."
  },
  "author": 3,
  "categories": [
    301
  ],
  "tags": [
    5541,
    1790
  ],
  "featured": false
}