{
  "id": 18576,
  "title": "Video: Nautic – Fresh Eyes",
  "date": "2012-12-04T23:58:39",
  "body": "You like cats? I like cats.\n\n**[Nautic](http://admin.crackintheroad.com/music/18297-new-nautic-fresh-eyes-ft-slime/ \"New: Nautic – Fresh Eyes (ft. Slime)\")** sure do like cats.\n\nThe video for **Nautic**’s debut track ‘_Fresh Eyes_’ dropped today. You should probably watch it.",
  "image": {
    "url": "https://admin.crackintheroad.com/wp-content/uploads/2012/12/nautic-100x100.png",
    "srcset": "https://admin.crackintheroad.com/wp-content/uploads/2012/12/nautic.png 539w, https://admin.crackintheroad.com/wp-content/uploads/2012/12/nautic-300x174.png 300w, https://admin.crackintheroad.com/wp-content/uploads/2012/12/nautic-50x29.png 50w"
  },
  "excerpt": {
    "full": "You like cats? I like cats. Nautic sure do like cats. The video for Nautic’s debut track ‘Fresh Eyes’ dropped today. You should probably watch it.",
    "short": "You like cats? I like cats."
  },
  "author": 3,
  "categories": [
    301,
    2269,
    2270
  ],
  "tags": [
    5897
  ],
  "featured": false
}