{
  "id": 14357,
  "title": "New MPfree: Orca Orca – Underground",
  "date": "2012-01-23T00:56:35",
  "body": "Since [Introducing](http://admin.crackintheroad.com/music/11358-introducing-orca-orca/) **Orca Orca** back in September last year, **Jim Hewitt** has come a long way in a short space of time, demonstrated perfectly on new track _Underground_. A reworking of a **Young Minds** [demo](http://orca-orca.bandcamp.com/track/underground) from 2010, it benefits from cleaner production making it sound less twee and more ready for live performances. There’s touches of **Mumm-ra**, **The Drums** and **Death Cab For Cutie** on _Underground_, all combining to form two and a half minutes of idyllic, indie-pop; well worthy of a listen. _Underground_ will form part of **Orca Orca’s** next release entitled _**Make Live**_, a limited edition cassette run featuring six new recordings and hand-painted artwork which drops 21 February.\n\n [Underground](http://soundcloud.com/orcaorca-1/underground) by [orca orca](http://soundcloud.com/orcaorca-1)",
  "image": {
    "url": "https://admin.crackintheroad.com/wp-content/uploads/2012/01/325673_278522928853643_252311724808097_766668_228292287_o-100x100.jpg",
    "srcset": "https://admin.crackintheroad.com/wp-content/uploads/2012/01/325673_278522928853643_252311724808097_766668_228292287_o-600x600.jpg 600w, https://admin.crackintheroad.com/wp-content/uploads/2012/01/325673_278522928853643_252311724808097_766668_228292287_o-150x150.jpg 150w, https://admin.crackintheroad.com/wp-content/uploads/2012/01/325673_278522928853643_252311724808097_766668_228292287_o-300x300.jpg 300w, https://admin.crackintheroad.com/wp-content/uploads/2012/01/325673_278522928853643_252311724808097_766668_228292287_o-100x100.jpg 100w"
  },
  "excerpt": {
    "full": "Since Introducing Orca Orca back in September last year, Jim Hewitt has come a long way in a short space of time, demonstrated perfectly on new track Underground. A reworking of a Young Minds demo from 2010, it benefits from cleaner production making it sound less twee and more ready for live performances. There’s touches \\[…\\]",
    "short": "Since Introducing Orca Orca back in September last year, Jim Hewitt has come a long way in..."
  },
  "author": 2,
  "categories": [
    1749,
    301,
    2269
  ],
  "tags": [],
  "featured": false
}