{
  "id": 23368,
  "title": "New: Shinies – Taste",
  "date": "2013-07-26T12:56:40",
  "body": "Mancunian rascals **Shinies** are set to release their debut EP **_Tangle_** later in the year, through Dirty Bingo, and have just released the first track to be lifted from said release.\n\n_Taste_ is yet another example of why they’re one of the UK’s most underrated new artists, with their cutting wit and raucous, noise-pop stylings, it’s arguably their finest outing to date. In a time when UK guitar music is pretty much flat on its arse (Palma Violets, Peace, blah you know the rest), **Shinies** are a twinkling star of hope. Check out _Taste_ below, and keep your eyes peeled for their EP, out 12 August.",
  "image": {
    "url": "https://admin.crackintheroad.com/wp-content/uploads/2013/07/1044367_380810512031269_1402696914_n-50x50.jpg",
    "srcset": "https://admin.crackintheroad.com/wp-content/uploads/2013/07/1044367_380810512031269_1402696914_n-600x600.jpg 600w, https://admin.crackintheroad.com/wp-content/uploads/2013/07/1044367_380810512031269_1402696914_n-150x150.jpg 150w, https://admin.crackintheroad.com/wp-content/uploads/2013/07/1044367_380810512031269_1402696914_n-300x300.jpg 300w, https://admin.crackintheroad.com/wp-content/uploads/2013/07/1044367_380810512031269_1402696914_n-100x100.jpg 100w, https://admin.crackintheroad.com/wp-content/uploads/2013/07/1044367_380810512031269_1402696914_n-50x50.jpg 50w, https://admin.crackintheroad.com/wp-content/uploads/2013/07/1044367_380810512031269_1402696914_n.jpg 612w"
  },
  "excerpt": {
    "full": "Mancunian rascals Shinies are set to release their debut EP Tangle later in the year, through Dirty Bingo, and have just released the first track to be lifted from said release. Taste is yet another example of why they’re one of the UK’s most underrated new artists, with their cutting wit and raucous, noise-pop stylings, \\[…\\]",
    "short": "Mancunian rascals Shinies are set to release their debut EP Tangle later in the year, thro..."
  },
  "author": 2,
  "categories": [
    301,
    2269
  ],
  "tags": [],
  "featured": false
}