{
  "id": 27627,
  "title": "New: Boots – Alright / Ride Ride Ride",
  "date": "2014-03-25T23:37:35",
  "body": "As much as other websites might have you believe with the tone of their coverage, **Boots** is no longer just ‘that Beyonce collaborator’.\n\nWith a Soundcloud steadily filling up with straight up jams, dropping not one but two new tracks today. From a vaguely Beastie Boys sounding _Alright_ that finds Boots rapping for the first time, to the Frank Ocean-esque _Ride Ride Ride_, Boots is rapidly making a name for himself as not just a producer and songwriter for others, but as a star in his own right. Check out both below.",
  "image": {
    "url": "https://admin.crackintheroad.com/wp-content/uploads/2014/03/1548003_460918774034756_1150408740_o-100x100.jpg",
    "srcset": "https://admin.crackintheroad.com/wp-content/uploads/2014/03/1548003_460918774034756_1150408740_o-600x600.jpg 600w, https://admin.crackintheroad.com/wp-content/uploads/2014/03/1548003_460918774034756_1150408740_o-150x150.jpg 150w, https://admin.crackintheroad.com/wp-content/uploads/2014/03/1548003_460918774034756_1150408740_o-300x300.jpg 300w, https://admin.crackintheroad.com/wp-content/uploads/2014/03/1548003_460918774034756_1150408740_o-100x100.jpg 100w"
  },
  "excerpt": {
    "full": "As much as other websites might have you believe with the tone of their coverage, Boots is no longer just ‘that Beyonce collaborator’. With a Soundcloud steadily filling up with straight up jams, dropping not one but two new tracks today. From a vaguely Beastie Boys sounding Alright that finds Boots rapping for the first \\[…\\]",
    "short": "As much as other websites might have you believe with the tone of their coverage, Boots is..."
  },
  "author": 2,
  "categories": [
    1749,
    301,
    2269
  ],
  "tags": [],
  "featured": false
}