{
  "id": 29198,
  "title": "New: Tora – Eat The Sun",
  "date": "2014-07-20T00:22:52",
  "body": "It’s quarter past one in the morning and the fire alarm in the building next to me has just gone off; thanks London.\n\nAnyway, lovely coincidence, Aussie outfit **Tora** have just uploaded this new gem, _Eat The Sun_. Another slice of super-chilled out electronic-pop, part James Blake, part SOHN, it’s a further development of their sound, and also a worthy reminder of the strength of their [previous material](https://soundcloud.com/toramusic). Check out Eat The Sun below.",
  "image": {
    "url": "https://admin.crackintheroad.com/wp-content/uploads/2014/07/1079081_612325662133360_214502100_o-100x100.jpg",
    "srcset": "https://admin.crackintheroad.com/wp-content/uploads/2014/07/1079081_612325662133360_214502100_o-600x600.jpg 600w, https://admin.crackintheroad.com/wp-content/uploads/2014/07/1079081_612325662133360_214502100_o-150x150.jpg 150w, https://admin.crackintheroad.com/wp-content/uploads/2014/07/1079081_612325662133360_214502100_o-300x300.jpg 300w, https://admin.crackintheroad.com/wp-content/uploads/2014/07/1079081_612325662133360_214502100_o-100x100.jpg 100w"
  },
  "excerpt": {
    "full": "It’s quarter past one in the morning and the fire alarm in the building next to me has just gone off; thanks London. Anyway, lovely coincidence, Aussie outfit Tora have just uploaded this new gem, Eat The Sun. Another slice of super-chilled out electronic-pop, part James Blake, part SOHN, it’s a further development of their \\[…\\]",
    "short": "It's quarter past one in the morning and the fire alarm in the building next to me has jus..."
  },
  "author": 2,
  "categories": [
    301,
    2269
  ],
  "tags": [],
  "featured": false
}