{
  "id": 34015,
  "title": "New: Sam Lynch – Mess You Made",
  "date": "2017-10-26T20:50:14",
  "body": "Love the intimacy to the songwriting here from **Sam Lynch**.\n\nAnyone who has been in a messy, turbulent relationship can probably sympathise with large portions of the lyrics here; the sense of pointlessly fighting with someone, when all you want to do is the absolute opposite. Touches of Julien Baker and Phoebe Bridgers seep in at times, with Lynch’s real heart on sleeve songwriting. Check it out below.",
  "image": {
    "url": "https://admin.crackintheroad.com/wp-content/uploads/2017/10/18952531_1218010484987698_527935163470832646_n-150x150.jpg",
    "srcset": "https://admin.crackintheroad.com/wp-content/uploads/2017/10/18952531_1218010484987698_527935163470832646_n.jpg 900w, https://admin.crackintheroad.com/wp-content/uploads/2017/10/18952531_1218010484987698_527935163470832646_n-300x202.jpg 300w, https://admin.crackintheroad.com/wp-content/uploads/2017/10/18952531_1218010484987698_527935163470832646_n-768x516.jpg 768w, https://admin.crackintheroad.com/wp-content/uploads/2017/10/18952531_1218010484987698_527935163470832646_n-50x34.jpg 50w"
  },
  "excerpt": {
    "full": "Love the intimacy to the songwriting here from Sam Lynch. Anyone who has been in a messy, turbulent relationship can probably sympathise with large portions of the lyrics here; the sense of pointlessly fighting with someone, when all you want to do is the absolute opposite. Touches of Julien Baker and Phoebe Bridgers seep in \\[…\\]",
    "short": "Love the intimacy to the songwriting here from Sam Lynch."
  },
  "author": 2,
  "categories": [
    301,
    2269
  ],
  "tags": [],
  "featured": false
}